[
    {
        "box": [
            117,
            92,
            177,
            141
        ],
        "text": "",
        "label": "OTHER",
        "words": [
            ""
        ],
        "id": 0,
        "boxes": [
            [
                117,
                92,
                177,
                141
            ]
        ],
        "links": []
    },
    {
        "box": [
            575,
            99,
            632,
            144
        ],
        "text": "",
        "label": "OTHER",
        "words": [
            ""
        ],
        "id": 1,
        "boxes": [
            [
                575,
                99,
                632,
                144
            ]
        ],
        "links": []
    },
    {
        "box": [
            524,
            205,
            556,
            219
        ],
        "text": "Date:",
        "label": "QUESTION",
        "words": [
            "Date:"
        ],
        "id": 2,
        "boxes": [
            [
                524,
                205,
                556,
                219
            ]
        ],
        "links": [
            [
                2,
                22
            ]
        ]
    },
    {
        "box": [
            119,
            388,
            180,
            403
        ],
        "text": "Market(s):",
        "label": "QUESTION",
        "words": [
            "Market(s):"
        ],
        "id": 3,
        "boxes": [
            [
                119,
                388,
                180,
                403
            ]
        ],
        "links": [
            [
                3,
                31
            ]
        ]
    },
    {
        "box": [
            120,
            543,
            151,
            557
        ],
        "text": "Male:",
        "label": "QUESTION",
        "words": [
            "Male:"
        ],
        "id": 4,
        "boxes": [
            [
                120,
                543,
                151,
                557
            ]
        ],
        "links": [
            [
                4,
                13
            ],
            [
                37,
                4
            ]
        ]
    },
    {
        "box": [
            119,
            560,
            164,
            573
        ],
        "text": "Female:",
        "label": "QUESTION",
        "words": [
            "Female:"
        ],
        "id": 5,
        "boxes": [
            [
                119,
                560,
                164,
                573
            ]
        ],
        "links": [
            [
                5,
                14
            ],
            [
                37,
                5
            ]
        ]
    },
    {
        "box": [
            187,
            606,
            232,
            620
        ],
        "text": "Bogot\u00e1:",
        "label": "QUESTION",
        "words": [
            "Bogot\u00e1:"
        ],
        "id": 6,
        "boxes": [
            [
                187,
                606,
                232,
                620
            ]
        ],
        "links": [
            [
                6,
                43
            ],
            [
                42,
                6
            ]
        ]
    },
    {
        "box": [
            189,
            635,
            242,
            650
        ],
        "text": "Medellin:",
        "label": "QUESTION",
        "words": [
            "Medellin:"
        ],
        "id": 7,
        "boxes": [
            [
                189,
                635,
                242,
                650
            ]
        ],
        "links": [
            [
                7,
                45
            ],
            [
                42,
                7
            ]
        ]
    },
    {
        "box": [
            120,
            670,
            151,
            683
        ],
        "text": "Note:",
        "label": "QUESTION",
        "words": [
            "Note:"
        ],
        "id": 8,
        "boxes": [
            [
                120,
                670,
                151,
                683
            ]
        ],
        "links": [
            [
                8,
                46
            ]
        ]
    },
    {
        "box": [
            218,
            205,
            229,
            219
        ],
        "text": "#",
        "label": "ANSWER",
        "words": [
            "#"
        ],
        "id": 9,
        "boxes": [
            [
                218,
                205,
                229,
                219
            ]
        ],
        "links": [
            [
                20,
                9
            ]
        ]
    },
    {
        "box": [
            219,
            270,
            251,
            284
        ],
        "text": "Other",
        "label": "ANSWER",
        "words": [
            "Other"
        ],
        "id": 10,
        "boxes": [
            [
                219,
                270,
                251,
                284
            ]
        ],
        "links": [
            [
                21,
                10
            ]
        ]
    },
    {
        "box": [
            313,
            239,
            383,
            250
        ],
        "text": "COLOMBIA",
        "label": "ANSWER",
        "words": [
            "COLOMBIA"
        ],
        "id": 11,
        "boxes": [
            [
                313,
                239,
                383,
                250
            ]
        ],
        "links": [
            [
                21,
                11
            ]
        ]
    },
    {
        "box": [
            311,
            254,
            352,
            267
        ],
        "text": "KOOL",
        "label": "ANSWER",
        "words": [
            "KOOL"
        ],
        "id": 12,
        "boxes": [
            [
                311,
                254,
                352,
                267
            ]
        ],
        "links": [
            [
                21,
                12
            ]
        ]
    },
    {
        "box": [
            190,
            541,
            215,
            559
        ],
        "text": "60%",
        "label": "ANSWER",
        "words": [
            "60%"
        ],
        "id": 13,
        "boxes": [
            [
                190,
                541,
                215,
                559
            ]
        ],
        "links": [
            [
                4,
                13
            ]
        ]
    },
    {
        "box": [
            190,
            559,
            215,
            570
        ],
        "text": "40%",
        "label": "ANSWER",
        "words": [
            "40%"
        ],
        "id": 14,
        "boxes": [
            [
                190,
                559,
                215,
                570
            ]
        ],
        "links": [
            [
                5,
                14
            ]
        ]
    },
    {
        "box": [
            120,
            444,
            131,
            455
        ],
        "text": "1)",
        "label": "OTHER",
        "words": [
            "1)"
        ],
        "id": 15,
        "boxes": [
            [
                120,
                444,
                131,
                455
            ]
        ],
        "links": []
    },
    {
        "box": [
            120,
            459,
            131,
            472
        ],
        "text": "2)",
        "label": "OTHER",
        "words": [
            "2)"
        ],
        "id": 16,
        "boxes": [
            [
                120,
                459,
                131,
                472
            ]
        ],
        "links": []
    },
    {
        "box": [
            122,
            475,
            132,
            488
        ],
        "text": "3)",
        "label": "OTHER",
        "words": [
            "3)"
        ],
        "id": 17,
        "boxes": [
            [
                122,
                475,
                132,
                488
            ]
        ],
        "links": []
    },
    {
        "box": [
            122,
            492,
            133,
            505
        ],
        "text": "4)",
        "label": "OTHER",
        "words": [
            "4)"
        ],
        "id": 18,
        "boxes": [
            [
                122,
                492,
                133,
                505
            ]
        ],
        "links": []
    },
    {
        "text": "Market Research - Initiating Project Brief",
        "box": [
            233,
            155,
            539,
            177
        ],
        "label": "HEADER",
        "words": [
            "Market",
            "Research",
            "-",
            "Initiating",
            "Project",
            "Brief"
        ],
        "id": 19,
        "boxes": [
            [
                233,
                155,
                287,
                173
            ],
            [
                292,
                156,
                358,
                174
            ],
            [
                360,
                159,
                368,
                172
            ],
            [
                370,
                156,
                440,
                177
            ],
            [
                444,
                155,
                496,
                176
            ],
            [
                500,
                156,
                539,
                176
            ]
        ],
        "links": []
    },
    {
        "text": "Brief Number",
        "box": [
            124,
            204,
            208,
            218
        ],
        "label": "QUESTION",
        "words": [
            "Brief",
            "Number"
        ],
        "id": 20,
        "boxes": [
            [
                124,
                204,
                155,
                218
            ],
            [
                156,
                205,
                208,
                218
            ]
        ],
        "links": [
            [
                20,
                9
            ]
        ]
    },
    {
        "text": "Client Group:",
        "box": [
            120,
            239,
            201,
            253
        ],
        "label": "QUESTION",
        "words": [
            "Client",
            "Group:"
        ],
        "id": 21,
        "boxes": [
            [
                120,
                239,
                156,
                253
            ],
            [
                159,
                239,
                201,
                253
            ]
        ],
        "links": [
            [
                21,
                23
            ],
            [
                21,
                11
            ],
            [
                21,
                24
            ],
            [
                21,
                10
            ],
            [
                21,
                12
            ]
        ]
    },
    {
        "text": "02/ 12/ 98",
        "box": [
            573,
            205,
            624,
            218
        ],
        "label": "ANSWER",
        "words": [
            "02/",
            "12/",
            "98"
        ],
        "id": 22,
        "boxes": [
            [
                573,
                205,
                588,
                218
            ],
            [
                588,
                205,
                605,
                218
            ],
            [
                606,
                205,
                624,
                218
            ]
        ],
        "links": [
            [
                2,
                22
            ]
        ]
    },
    {
        "text": "R. B. U.",
        "box": [
            216,
            237,
            256,
            250
        ],
        "label": "ANSWER",
        "words": [
            "R.",
            "B.",
            "U."
        ],
        "id": 23,
        "boxes": [
            [
                216,
                237,
                231,
                250
            ],
            [
                232,
                237,
                243,
                250
            ],
            [
                243,
                237,
                256,
                250
            ]
        ],
        "links": [
            [
                21,
                23
            ]
        ]
    },
    {
        "text": "Brand Group",
        "box": [
            221,
            254,
            293,
            267
        ],
        "label": "ANSWER",
        "words": [
            "Brand",
            "Group"
        ],
        "id": 24,
        "boxes": [
            [
                221,
                254,
                255,
                267
            ],
            [
                257,
                254,
                293,
                267
            ]
        ],
        "links": [
            [
                21,
                24
            ]
        ]
    },
    {
        "text": "Client Contact:",
        "box": [
            117,
            303,
            205,
            318
        ],
        "label": "QUESTION",
        "words": [
            "Client",
            "Contact:"
        ],
        "id": 25,
        "boxes": [
            [
                117,
                303,
                152,
                318
            ],
            [
                156,
                303,
                205,
                317
            ]
        ],
        "links": [
            [
                25,
                26
            ]
        ]
    },
    {
        "text": "Maria Helena Arg\u00fcelles/ Edwin Garcia",
        "box": [
            219,
            303,
            354,
            334
        ],
        "label": "ANSWER",
        "words": [
            "Maria",
            "Helena",
            "Arg\u00fcelles/",
            "Edwin",
            "Garcia"
        ],
        "id": 26,
        "boxes": [
            [
                219,
                303,
                253,
                318
            ],
            [
                256,
                303,
                295,
                317
            ],
            [
                297,
                303,
                354,
                316
            ],
            [
                219,
                320,
                255,
                333
            ],
            [
                258,
                320,
                296,
                334
            ]
        ],
        "links": [
            [
                25,
                26
            ]
        ]
    },
    {
        "text": "Research Liaison:",
        "box": [
            394,
            303,
            499,
            318
        ],
        "label": "QUESTION",
        "words": [
            "Research",
            "Liaison:"
        ],
        "id": 27,
        "boxes": [
            [
                394,
                304,
                447,
                318
            ],
            [
                450,
                303,
                499,
                317
            ]
        ],
        "links": [
            [
                27,
                28
            ]
        ]
    },
    {
        "text": "Camilo Concha/ Andrea Suarez",
        "box": [
            504,
            302,
            634,
            334
        ],
        "label": "ANSWER",
        "words": [
            "Camilo",
            "Concha/",
            "Andrea",
            "Suarez"
        ],
        "id": 28,
        "boxes": [
            [
                504,
                302,
                546,
                316
            ],
            [
                547,
                303,
                594,
                316
            ],
            [
                595,
                304,
                634,
                317
            ],
            [
                504,
                320,
                543,
                334
            ]
        ],
        "links": [
            [
                27,
                28
            ]
        ]
    },
    {
        "text": "Project Name/ Description",
        "box": [
            120,
            353,
            271,
            369
        ],
        "label": "QUESTION",
        "words": [
            "Project",
            "Name/",
            "Description"
        ],
        "id": 29,
        "boxes": [
            [
                120,
                355,
                161,
                369
            ],
            [
                163,
                353,
                201,
                368
            ],
            [
                201,
                355,
                271,
                369
            ]
        ],
        "links": [
            [
                29,
                30
            ]
        ]
    },
    {
        "text": "K001 vs. Marlboro Menthol Lights",
        "box": [
            274,
            352,
            472,
            369
        ],
        "label": "ANSWER",
        "words": [
            "K001",
            "vs.",
            "Marlboro",
            "Menthol",
            "Lights"
        ],
        "id": 30,
        "boxes": [
            [
                274,
                353,
                312,
                367
            ],
            [
                316,
                353,
                330,
                367
            ],
            [
                334,
                353,
                386,
                366
            ],
            [
                388,
                352,
                433,
                369
            ],
            [
                436,
                353,
                472,
                368
            ]
        ],
        "links": [
            [
                29,
                30
            ]
        ]
    },
    {
        "text": "Bogot\u00e1, Medellin and Barranquilla",
        "box": [
            183,
            388,
            373,
            403
        ],
        "label": "ANSWER",
        "words": [
            "Bogot\u00e1,",
            "Medellin",
            "and",
            "Barranquilla"
        ],
        "id": 31,
        "boxes": [
            [
                183,
                388,
                226,
                403
            ],
            [
                230,
                388,
                276,
                401
            ],
            [
                281,
                390,
                301,
                403
            ],
            [
                303,
                388,
                373,
                403
            ]
        ],
        "links": [
            [
                3,
                31
            ]
        ]
    },
    {
        "text": "Referent Brand(s):",
        "box": [
            120,
            426,
            226,
            441
        ],
        "label": "QUESTION",
        "words": [
            "Referent",
            "Brand(s):"
        ],
        "id": 32,
        "boxes": [
            [
                120,
                426,
                169,
                440
            ],
            [
                172,
                426,
                226,
                441
            ]
        ],
        "links": [
            [
                32,
                33
            ],
            [
                32,
                34
            ],
            [
                32,
                35
            ],
            [
                32,
                36
            ]
        ]
    },
    {
        "text": "Current Kool Filter King Colombia 1 1 mg tar @ 0. 51% menthol white tipping.",
        "box": [
            134,
            441,
            570,
            458
        ],
        "label": "ANSWER",
        "words": [
            "Current",
            "Kool",
            "Filter",
            "King",
            "Colombia",
            "1",
            "1",
            "mg",
            "tar",
            "@",
            "0.",
            "51%",
            "menthol",
            "white",
            "tipping."
        ],
        "id": 33,
        "boxes": [
            [
                134,
                444,
                175,
                455
            ],
            [
                179,
                444,
                204,
                455
            ],
            [
                207,
                443,
                238,
                454
            ],
            [
                240,
                443,
                267,
                456
            ],
            [
                271,
                441,
                327,
                455
            ],
            [
                331,
                443,
                337,
                454
            ],
            [
                338,
                443,
                342,
                454
            ],
            [
                346,
                446,
                364,
                457
            ],
            [
                367,
                444,
                385,
                455
            ],
            [
                388,
                441,
                402,
                456
            ],
            [
                404,
                441,
                415,
                454
            ],
            [
                415,
                441,
                440,
                455
            ],
            [
                443,
                443,
                490,
                456
            ],
            [
                493,
                443,
                524,
                456
            ],
            [
                527,
                441,
                570,
                458
            ]
        ],
        "links": [
            [
                32,
                33
            ]
        ]
    },
    {
        "text": "Kool Milds KS Japan 9mg tar @ 0. 56% menthol white tipping",
        "box": [
            135,
            458,
            483,
            472
        ],
        "label": "ANSWER",
        "words": [
            "Kool",
            "Milds",
            "KS",
            "Japan",
            "9mg",
            "tar",
            "@",
            "0.",
            "56%",
            "menthol",
            "white",
            "tipping"
        ],
        "id": 34,
        "boxes": [
            [
                135,
                458,
                160,
                471
            ],
            [
                165,
                458,
                196,
                471
            ],
            [
                200,
                458,
                217,
                471
            ],
            [
                219,
                458,
                253,
                472
            ],
            [
                257,
                458,
                279,
                472
            ],
            [
                282,
                461,
                300,
                471
            ],
            [
                304,
                458,
                317,
                472
            ],
            [
                320,
                459,
                330,
                470
            ],
            [
                331,
                459,
                355,
                470
            ],
            [
                358,
                459,
                405,
                470
            ],
            [
                409,
                458,
                437,
                471
            ],
            [
                441,
                458,
                483,
                472
            ]
        ],
        "links": [
            [
                32,
                34
            ]
        ]
    },
    {
        "text": "Kool KS. 9 mg tar, @ 0. 51% menthol white tipping",
        "box": [
            135,
            473,
            418,
            488
        ],
        "label": "ANSWER",
        "words": [
            "Kool",
            "KS.",
            "9",
            "mg",
            "tar,",
            "@",
            "0.",
            "51%",
            "menthol",
            "white",
            "tipping"
        ],
        "id": 35,
        "boxes": [
            [
                135,
                473,
                160,
                486
            ],
            [
                165,
                473,
                183,
                487
            ],
            [
                187,
                473,
                194,
                484
            ],
            [
                197,
                475,
                214,
                488
            ],
            [
                218,
                475,
                236,
                488
            ],
            [
                239,
                473,
                252,
                488
            ],
            [
                254,
                473,
                264,
                486
            ],
            [
                265,
                473,
                289,
                487
            ],
            [
                293,
                475,
                339,
                486
            ],
            [
                344,
                475,
                372,
                486
            ],
            [
                376,
                475,
                418,
                488
            ]
        ],
        "links": [
            [
                32,
                35
            ]
        ]
    },
    {
        "text": "Current Marlboro Lights Menthol King US 9mg tar @ 0. 66% menthol, white tipping.",
        "box": [
            135,
            490,
            602,
            507
        ],
        "label": "ANSWER",
        "words": [
            "Current",
            "Marlboro",
            "Lights",
            "Menthol",
            "King",
            "US",
            "9mg",
            "tar",
            "@",
            "0.",
            "66%",
            "menthol,",
            "white",
            "tipping."
        ],
        "id": 36,
        "boxes": [
            [
                135,
                490,
                176,
                504
            ],
            [
                179,
                490,
                231,
                503
            ],
            [
                233,
                490,
                267,
                504
            ],
            [
                270,
                490,
                316,
                504
            ],
            [
                320,
                490,
                345,
                504
            ],
            [
                349,
                492,
                370,
                505
            ],
            [
                373,
                492,
                397,
                506
            ],
            [
                401,
                493,
                419,
                504
            ],
            [
                422,
                490,
                435,
                505
            ],
            [
                439,
                490,
                450,
                503
            ],
            [
                448,
                490,
                473,
                504
            ],
            [
                475,
                492,
                524,
                505
            ],
            [
                528,
                492,
                557,
                505
            ],
            [
                560,
                492,
                602,
                507
            ]
        ],
        "links": [
            [
                32,
                36
            ]
        ]
    },
    {
        "text": "Consumer Segment(s):",
        "box": [
            120,
            524,
            249,
            539
        ],
        "label": "HEADER",
        "words": [
            "Consumer",
            "Segment(s):"
        ],
        "id": 37,
        "boxes": [
            [
                120,
                524,
                180,
                539
            ],
            [
                183,
                524,
                249,
                539
            ]
        ],
        "links": [
            [
                37,
                4
            ],
            [
                37,
                5
            ],
            [
                37,
                39
            ],
            [
                37,
                40
            ],
            [
                37,
                42
            ]
        ]
    },
    {
        "text": "18 -29 (100%)",
        "box": [
            190,
            574,
            265,
            589
        ],
        "label": "ANSWER",
        "words": [
            "18",
            "-29",
            "(100%)"
        ],
        "id": 38,
        "boxes": [
            [
                190,
                574,
                203,
                587
            ],
            [
                204,
                574,
                222,
                589
            ],
            [
                223,
                575,
                265,
                589
            ]
        ],
        "links": [
            [
                39,
                38
            ]
        ]
    },
    {
        "text": "By age:",
        "box": [
            122,
            575,
            162,
            589
        ],
        "label": "QUESTION",
        "words": [
            "By",
            "age:"
        ],
        "id": 39,
        "boxes": [
            [
                122,
                575,
                136,
                589
            ],
            [
                138,
                577,
                162,
                588
            ]
        ],
        "links": [
            [
                39,
                38
            ],
            [
                37,
                39
            ]
        ]
    },
    {
        "text": "BY SEL:",
        "box": [
            122,
            591,
            167,
            605
        ],
        "label": "QUESTION",
        "words": [
            "BY",
            "SEL:"
        ],
        "id": 40,
        "boxes": [
            [
                122,
                591,
                136,
                605
            ],
            [
                140,
                591,
                167,
                604
            ]
        ],
        "links": [
            [
                40,
                41
            ],
            [
                37,
                40
            ]
        ]
    },
    {
        "text": "AB1 (100%)",
        "box": [
            190,
            591,
            259,
            604
        ],
        "label": "ANSWER",
        "words": [
            "AB1",
            "(100%)"
        ],
        "id": 41,
        "boxes": [
            [
                190,
                591,
                215,
                602
            ],
            [
                218,
                591,
                259,
                604
            ]
        ],
        "links": [
            [
                40,
                41
            ]
        ]
    },
    {
        "text": "By City:",
        "box": [
            122,
            606,
            168,
            621
        ],
        "label": "HEADER",
        "words": [
            "By",
            "City:"
        ],
        "id": 42,
        "boxes": [
            [
                122,
                608,
                137,
                621
            ],
            [
                140,
                606,
                168,
                620
            ]
        ],
        "links": [
            [
                37,
                42
            ],
            [
                42,
                6
            ],
            [
                42,
                53
            ],
            [
                42,
                7
            ]
        ]
    },
    {
        "text": "KOOL Parent regular smokers 50% -alternate smokers 50%",
        "box": [
            249,
            605,
            572,
            622
        ],
        "label": "ANSWER",
        "words": [
            "KOOL",
            "Parent",
            "regular",
            "smokers",
            "50%",
            "-alternate",
            "smokers",
            "50%"
        ],
        "id": 43,
        "boxes": [
            [
                249,
                608,
                287,
                619
            ],
            [
                291,
                605,
                325,
                620
            ],
            [
                328,
                608,
                366,
                619
            ],
            [
                369,
                608,
                416,
                619
            ],
            [
                418,
                608,
                442,
                619
            ],
            [
                444,
                608,
                497,
                622
            ],
            [
                500,
                609,
                546,
                619
            ],
            [
                547,
                606,
                572,
                619
            ]
        ],
        "links": [
            [
                6,
                43
            ]
        ]
    },
    {
        "text": "KOOL Parent regular smokers 50% -alternate smokers 50%",
        "box": [
            249,
            622,
            572,
            636
        ],
        "label": "ANSWER",
        "words": [
            "KOOL",
            "Parent",
            "regular",
            "smokers",
            "50%",
            "-alternate",
            "smokers",
            "50%"
        ],
        "id": 44,
        "boxes": [
            [
                249,
                622,
                287,
                635
            ],
            [
                289,
                622,
                324,
                635
            ],
            [
                327,
                623,
                366,
                636
            ],
            [
                369,
                624,
                415,
                634
            ],
            [
                416,
                622,
                444,
                636
            ],
            [
                446,
                623,
                498,
                634
            ],
            [
                499,
                623,
                546,
                634
            ],
            [
                547,
                622,
                572,
                635
            ]
        ],
        "links": [
            [
                53,
                44
            ]
        ]
    },
    {
        "text": "KOOL Parent regular smokers 50% -alternate smokers 50%",
        "box": [
            250,
            638,
            574,
            652
        ],
        "label": "ANSWER",
        "words": [
            "KOOL",
            "Parent",
            "regular",
            "smokers",
            "50%",
            "-alternate",
            "smokers",
            "50%"
        ],
        "id": 45,
        "boxes": [
            [
                250,
                638,
                286,
                651
            ],
            [
                291,
                638,
                325,
                651
            ],
            [
                327,
                638,
                366,
                651
            ],
            [
                369,
                640,
                415,
                650
            ],
            [
                416,
                638,
                443,
                651
            ],
            [
                444,
                638,
                497,
                649
            ],
            [
                499,
                640,
                545,
                650
            ],
            [
                549,
                638,
                574,
                652
            ]
        ],
        "links": [
            [
                7,
                45
            ]
        ]
    },
    {
        "text": "In order to establish a quantitative basis for determining the winning product, results will be",
        "box": [
            154,
            668,
            651,
            686
        ],
        "label": "ANSWER",
        "words": [
            "In",
            "order",
            "to",
            "establish",
            "a",
            "quantitative",
            "basis",
            "for",
            "determining",
            "the",
            "winning",
            "product,",
            "results",
            "will",
            "be"
        ],
        "id": 46,
        "boxes": [
            [
                154,
                670,
                167,
                683
            ],
            [
                169,
                670,
                197,
                683
            ],
            [
                200,
                670,
                211,
                683
            ],
            [
                214,
                669,
                260,
                683
            ],
            [
                263,
                672,
                271,
                682
            ],
            [
                272,
                669,
                336,
                684
            ],
            [
                341,
                669,
                368,
                683
            ],
            [
                372,
                669,
                387,
                683
            ],
            [
                388,
                668,
                454,
                686
            ],
            [
                458,
                672,
                476,
                683
            ],
            [
                480,
                669,
                522,
                684
            ],
            [
                527,
                670,
                572,
                685
            ],
            [
                575,
                672,
                611,
                686
            ],
            [
                613,
                670,
                635,
                683
            ],
            [
                638,
                672,
                651,
                683
            ]
        ],
        "links": [
            [
                8,
                46
            ]
        ]
    },
    {
        "text": "Alternate 60%, Regular 40%.",
        "box": [
            233,
            686,
            391,
            700
        ],
        "label": "ANSWER",
        "words": [
            "Alternate",
            "60%,",
            "Regular",
            "40%."
        ],
        "id": 47,
        "boxes": [
            [
                233,
                686,
                283,
                700
            ],
            [
                286,
                686,
                315,
                700
            ],
            [
                318,
                687,
                360,
                700
            ],
            [
                363,
                686,
                391,
                700
            ]
        ],
        "links": [
            [
                52,
                47
            ]
        ]
    },
    {
        "text": "Background Problem Definition:",
        "box": [
            119,
            722,
            310,
            736
        ],
        "label": "QUESTION",
        "words": [
            "Background",
            "Problem",
            "Definition:"
        ],
        "id": 48,
        "boxes": [
            [
                119,
                722,
                192,
                736
            ],
            [
                191,
                722,
                245,
                735
            ],
            [
                247,
                722,
                310,
                735
            ]
        ],
        "links": [
            [
                48,
                49
            ],
            [
                48,
                50
            ]
        ]
    },
    {
        "text": "On September 1 97, PMI simultaneously launched Marlboro Menthol KS Box (16mg tar and Menthol Lights KS Box (9mg tar) in Colombia. These two products became KOOL's direct competitors (Premium Menthol Brands).",
        "box": [
            122,
            736,
            653,
            784
        ],
        "label": "ANSWER",
        "words": [
            "On",
            "September",
            "1",
            "97,",
            "PMI",
            "simultaneously",
            "launched",
            "Marlboro",
            "Menthol",
            "KS",
            "Box",
            "(16mg",
            "tar",
            "and",
            "Menthol",
            "Lights",
            "KS",
            "Box",
            "(9mg",
            "tar)",
            "in",
            "Colombia.",
            "These",
            "two",
            "products",
            "became",
            "KOOL's",
            "direct",
            "competitors",
            "(Premium",
            "Menthol",
            "Brands)."
        ],
        "id": 49,
        "boxes": [
            [
                122,
                737,
                137,
                748
            ],
            [
                142,
                739,
                196,
                750
            ],
            [
                204,
                739,
                217,
                750
            ],
            [
                221,
                739,
                236,
                750
            ],
            [
                242,
                737,
                267,
                750
            ],
            [
                271,
                737,
                353,
                751
            ],
            [
                358,
                737,
                407,
                750
            ],
            [
                411,
                736,
                465,
                751
            ],
            [
                468,
                737,
                514,
                751
            ],
            [
                518,
                737,
                536,
                750
            ],
            [
                542,
                737,
                563,
                750
            ],
            [
                567,
                737,
                603,
                751
            ],
            [
                609,
                740,
                627,
                750
            ],
            [
                634,
                739,
                652,
                749
            ],
            [
                122,
                753,
                168,
                767
            ],
            [
                172,
                753,
                206,
                766
            ],
            [
                211,
                753,
                229,
                766
            ],
            [
                233,
                753,
                255,
                766
            ],
            [
                260,
                753,
                291,
                767
            ],
            [
                296,
                753,
                314,
                766
            ],
            [
                320,
                753,
                333,
                764
            ],
            [
                338,
                753,
                394,
                766
            ],
            [
                404,
                753,
                438,
                766
            ],
            [
                441,
                754,
                463,
                764
            ],
            [
                469,
                754,
                515,
                767
            ],
            [
                521,
                753,
                564,
                766
            ],
            [
                568,
                754,
                615,
                767
            ],
            [
                622,
                754,
                653,
                767
            ],
            [
                122,
                770,
                183,
                783
            ],
            [
                186,
                770,
                240,
                783
            ],
            [
                242,
                768,
                288,
                781
            ],
            [
                292,
                767,
                337,
                784
            ]
        ],
        "links": [
            [
                48,
                49
            ]
        ]
    },
    {
        "text": "At the same time KOOL replaced its product with a milder 11mg cigarette (the same KOOL Milds but with a 27mm cork tipping).",
        "box": [
            122,
            785,
            649,
            817
        ],
        "label": "ANSWER",
        "words": [
            "At",
            "the",
            "same",
            "time",
            "KOOL",
            "replaced",
            "its",
            "product",
            "with",
            "a",
            "milder",
            "11mg",
            "cigarette",
            "(the",
            "same",
            "KOOL",
            "Milds",
            "but",
            "with",
            "a",
            "27mm",
            "cork",
            "tipping)."
        ],
        "id": 50,
        "boxes": [
            [
                122,
                785,
                136,
                798
            ],
            [
                140,
                786,
                157,
                797
            ],
            [
                161,
                786,
                190,
                797
            ],
            [
                191,
                785,
                222,
                798
            ],
            [
                225,
                785,
                264,
                798
            ],
            [
                270,
                786,
                315,
                799
            ],
            [
                318,
                785,
                332,
                796
            ],
            [
                337,
                785,
                379,
                800
            ],
            [
                384,
                785,
                409,
                798
            ],
            [
                415,
                788,
                422,
                796
            ],
            [
                426,
                785,
                462,
                799
            ],
            [
                466,
                785,
                497,
                799
            ],
            [
                500,
                786,
                549,
                800
            ],
            [
                554,
                785,
                576,
                799
            ],
            [
                582,
                786,
                609,
                797
            ],
            [
                615,
                785,
                649,
                799
            ],
            [
                122,
                802,
                153,
                816
            ],
            [
                155,
                802,
                172,
                816
            ],
            [
                176,
                802,
                198,
                815
            ],
            [
                201,
                803,
                208,
                814
            ],
            [
                211,
                802,
                246,
                816
            ],
            [
                249,
                802,
                271,
                816
            ],
            [
                275,
                800,
                321,
                817
            ]
        ],
        "links": [
            [
                48,
                50
            ]
        ]
    },
    {
        "text": "440026083 PRODUCED FROM B &W WEB SITE",
        "box": [
            0,
            953,
            231,
            983
        ],
        "label": "OTHER",
        "words": [
            "440026083",
            "PRODUCED",
            "FROM",
            "B",
            "&W",
            "WEB",
            "SITE"
        ],
        "id": 51,
        "boxes": [
            [
                0,
                953,
                78,
                966
            ],
            [
                0,
                968,
                70,
                983
            ],
            [
                77,
                968,
                118,
                982
            ],
            [
                122,
                969,
                135,
                982
            ],
            [
                135,
                968,
                153,
                981
            ],
            [
                158,
                969,
                187,
                982
            ],
            [
                193,
                968,
                231,
                982
            ]
        ],
        "links": []
    },
    {
        "text": "weighted as follows:",
        "box": [
            120,
            686,
            230,
            700
        ],
        "label": "QUESTION",
        "words": [
            "weighted",
            "as",
            "follows:"
        ],
        "id": 52,
        "boxes": [
            [
                120,
                687,
                169,
                700
            ],
            [
                172,
                689,
                185,
                700
            ],
            [
                187,
                686,
                230,
                700
            ]
        ],
        "links": [
            [
                52,
                47
            ]
        ]
    },
    {
        "text": "B/ quilla:",
        "box": [
            190,
            622,
            238,
            636
        ],
        "label": "QUESTION",
        "words": [
            "B/",
            "quilla:"
        ],
        "id": 53,
        "boxes": [
            [
                190,
                623,
                203,
                634
            ],
            [
                204,
                622,
                238,
                636
            ]
        ],
        "links": [
            [
                53,
                44
            ],
            [
                42,
                53
            ]
        ]
    }
]