[
    {
        "box": [
            89,
            232,
            135,
            250
        ],
        "text": "Date:",
        "label": "QUESTION",
        "words": [
            "Date:"
        ],
        "id": 0,
        "boxes": [
            [
                89,
                232,
                135,
                250
            ]
        ],
        "links": []
    },
    {
        "box": [
            690,
            775,
            710,
            874
        ],
        "text": "81186212",
        "label": "OTHER",
        "words": [
            "81186212"
        ],
        "id": 1,
        "boxes": [
            [
                690,
                775,
                710,
                874
            ]
        ],
        "links": []
    },
    {
        "box": [
            89,
            943,
            128,
            961
        ],
        "text": "4/79",
        "label": "OTHER",
        "words": [
            "4/79"
        ],
        "id": 2,
        "boxes": [
            [
                89,
                943,
                128,
                961
            ]
        ],
        "links": []
    },
    {
        "text": "New Competitive Activity",
        "box": [
            254,
            56,
            478,
            76
        ],
        "label": "HEADER",
        "words": [
            "New",
            "Competitive",
            "Activity"
        ],
        "id": 3,
        "boxes": [
            [
                254,
                57,
                285,
                74
            ],
            [
                292,
                56,
                394,
                71
            ],
            [
                401,
                59,
                478,
                76
            ]
        ],
        "links": []
    },
    {
        "text": "Please fill in the following information, as appropriate and send to C. W. Toti, Marketing Services Director, at the New York Office. Thank you.",
        "box": [
            87,
            109,
            646,
            163
        ],
        "label": "OTHER",
        "words": [
            "Please",
            "fill",
            "in",
            "the",
            "following",
            "information,",
            "as",
            "appropriate",
            "and",
            "send",
            "to",
            "C.",
            "W.",
            "Toti,",
            "Marketing",
            "Services",
            "Director,",
            "at",
            "the",
            "New",
            "York",
            "Office.",
            "Thank you."
        ],
        "id": 4,
        "boxes": [
            [
                89,
                112,
                148,
                129
            ],
            [
                156,
                109,
                191,
                129
            ],
            [
                198,
                109,
                219,
                127
            ],
            [
                229,
                109,
                261,
                126
            ],
            [
                267,
                110,
                349,
                127
            ],
            [
                356,
                110,
                462,
                127
            ],
            [
                472,
                110,
                497,
                130
            ],
            [
                497,
                113,
                605,
                130
            ],
            [
                610,
                115,
                646,
                129
            ],
            [
                89,
                131,
                130,
                146
            ],
            [
                138,
                130,
                155,
                148
            ],
            [
                162,
                130,
                180,
                145
            ],
            [
                189,
                130,
                210,
                145
            ],
            [
                218,
                128,
                261,
                145
            ],
            [
                274,
                130,
                356,
                145
            ],
            [
                366,
                131,
                440,
                145
            ],
            [
                446,
                130,
                528,
                145
            ],
            [
                535,
                133,
                560,
                144
            ],
            [
                567,
                133,
                596,
                147
            ],
            [
                87,
                147,
                121,
                162
            ],
            [
                127,
                148,
                166,
                162
            ],
            [
                172,
                147,
                235,
                162
            ],
            [
                256,
                149,
                345,
                163
            ]
        ],
        "links": []
    },
    {
        "text": "Reported by:",
        "box": [
            85,
            198,
            200,
            215
        ],
        "label": "QUESTION",
        "words": [
            "Reported",
            "by:"
        ],
        "id": 5,
        "boxes": [
            [
                85,
                198,
                167,
                215
            ],
            [
                175,
                198,
                200,
                215
            ]
        ],
        "links": []
    },
    {
        "text": "Manufacturer & Brand:",
        "box": [
            92,
            267,
            282,
            284
        ],
        "label": "QUESTION",
        "words": [
            "Manufacturer",
            "&",
            "Brand:"
        ],
        "id": 6,
        "boxes": [
            [
                92,
                267,
                202,
                284
            ],
            [
                209,
                270,
                223,
                284
            ],
            [
                228,
                267,
                282,
                284
            ]
        ],
        "links": []
    },
    {
        "text": "Type of product, size(s) & list price:",
        "box": [
            89,
            303,
            438,
            321
        ],
        "label": "QUESTION",
        "words": [
            "Type",
            "of",
            "product,",
            "size(s)",
            "&",
            "list",
            "price:"
        ],
        "id": 7,
        "boxes": [
            [
                89,
                303,
                131,
                320
            ],
            [
                137,
                303,
                157,
                317
            ],
            [
                163,
                306,
                234,
                319
            ],
            [
                243,
                306,
                306,
                321
            ],
            [
                316,
                304,
                334,
                318
            ],
            [
                339,
                303,
                374,
                320
            ],
            [
                381,
                303,
                438,
                320
            ]
        ],
        "links": []
    },
    {
        "text": "Extent of distribution:",
        "box": [
            91,
            408,
            301,
            425
        ],
        "label": "QUESTION",
        "words": [
            "Extent",
            "of",
            "distribution:"
        ],
        "id": 8,
        "boxes": [
            [
                91,
                411,
                150,
                425
            ],
            [
                154,
                408,
                178,
                423
            ],
            [
                182,
                409,
                301,
                424
            ]
        ],
        "links": []
    },
    {
        "text": "Information and hearsay from outside contacts:",
        "box": [
            91,
            514,
            510,
            530
        ],
        "label": "QUESTION",
        "words": [
            "Information",
            "and",
            "hearsay",
            "from",
            "outside",
            "contacts:"
        ],
        "id": 9,
        "boxes": [
            [
                91,
                515,
                196,
                529
            ],
            [
                200,
                515,
                232,
                528
            ],
            [
                237,
                515,
                304,
                529
            ],
            [
                310,
                514,
                352,
                529
            ],
            [
                356,
                515,
                426,
                529
            ],
            [
                430,
                515,
                510,
                530
            ]
        ],
        "links": []
    },
    {
        "text": "Further information (please attach any relevant materials; POS, advertising, brochures, etc.):",
        "box": [
            89,
            684,
            621,
            719
        ],
        "label": "QUESTION",
        "words": [
            "Further",
            "information",
            "(please",
            "attach",
            "any",
            "relevant",
            "materials;",
            "POS,",
            "advertising,",
            "brochures,",
            "etc.):"
        ],
        "id": 10,
        "boxes": [
            [
                92,
                686,
                159,
                701
            ],
            [
                165,
                686,
                266,
                700
            ],
            [
                277,
                686,
                338,
                703
            ],
            [
                345,
                687,
                406,
                701
            ],
            [
                411,
                687,
                440,
                702
            ],
            [
                447,
                684,
                522,
                704
            ],
            [
                527,
                686,
                621,
                704
            ],
            [
                89,
                705,
                127,
                716
            ],
            [
                135,
                703,
                244,
                718
            ],
            [
                254,
                704,
                345,
                718
            ],
            [
                355,
                704,
                409,
                719
            ]
        ],
        "links": []
    }
]