[
    {
        "box": [
            78,
            124,
            100,
            139
        ],
        "text": "TO:",
        "label": "QUESTION",
        "words": [
            "TO:"
        ],
        "id": 0,
        "boxes": [
            [
                78,
                124,
                100,
                139
            ]
        ],
        "links": [
            [
                0,
                14
            ]
        ]
    },
    {
        "box": [
            77,
            152,
            122,
            166
        ],
        "text": "FROM:",
        "label": "QUESTION",
        "words": [
            "FROM:"
        ],
        "id": 1,
        "boxes": [
            [
                77,
                152,
                122,
                166
            ]
        ],
        "links": [
            [
                1,
                16
            ]
        ]
    },
    {
        "box": [
            608,
            126,
            664,
            139
        ],
        "text": "1/24/97",
        "label": "ANSWER",
        "words": [
            "1/24/97"
        ],
        "id": 2,
        "boxes": [
            [
                608,
                126,
                664,
                139
            ]
        ],
        "links": [
            [
                15,
                2
            ]
        ]
    },
    {
        "box": [
            233,
            453,
            244,
            464
        ],
        "text": "2",
        "label": "ANSWER",
        "words": [
            "2"
        ],
        "id": 3,
        "boxes": [
            [
                233,
                453,
                244,
                464
            ]
        ],
        "links": [
            [
                26,
                3
            ]
        ]
    },
    {
        "box": [
            233,
            480,
            244,
            493
        ],
        "text": "1",
        "label": "ANSWER",
        "words": [
            "1"
        ],
        "id": 4,
        "boxes": [
            [
                233,
                480,
                244,
                493
            ]
        ],
        "links": [
            [
                28,
                4
            ]
        ]
    },
    {
        "box": [
            429,
            482,
            440,
            495
        ],
        "text": "1",
        "label": "ANSWER",
        "words": [
            "1"
        ],
        "id": 5,
        "boxes": [
            [
                429,
                482,
                440,
                495
            ]
        ],
        "links": [
            [
                35,
                5
            ]
        ]
    },
    {
        "box": [
            430,
            494,
            440,
            507
        ],
        "text": "1",
        "label": "ANSWER",
        "words": [
            "1"
        ],
        "id": 6,
        "boxes": [
            [
                430,
                494,
                440,
                507
            ]
        ],
        "links": [
            [
                36,
                6
            ]
        ]
    },
    {
        "box": [
            306,
            563,
            348,
            576
        ],
        "text": "ITEMS",
        "label": "QUESTION",
        "words": [
            "ITEMS"
        ],
        "id": 7,
        "boxes": [
            [
                306,
                563,
                348,
                576
            ]
        ],
        "links": [
            [
                7,
                39
            ],
            [
                7,
                40
            ]
        ]
    },
    {
        "box": [
            413,
            811,
            462,
            836
        ],
        "text": "zbulan",
        "label": "ANSWER",
        "words": [
            "zbulan"
        ],
        "id": 8,
        "boxes": [
            [
                413,
                811,
                462,
                836
            ]
        ],
        "links": [
            [
                45,
                8
            ]
        ]
    },
    {
        "box": [
            676,
            768,
            698,
            870
        ],
        "text": "82254765",
        "label": "OTHER",
        "words": [
            "82254765"
        ],
        "id": 9,
        "boxes": [
            [
                676,
                768,
                698,
                870
            ]
        ],
        "links": []
    },
    {
        "box": [
            640,
            934,
            683,
            947
        ],
        "text": "01/17/97",
        "label": "OTHER",
        "words": [
            "01/17/97"
        ],
        "id": 10,
        "boxes": [
            [
                640,
                934,
                683,
                947
            ]
        ],
        "links": []
    },
    {
        "box": [
            50,
            934,
            110,
            948
        ],
        "text": "REQFORM",
        "label": "OTHER",
        "words": [
            "REQFORM"
        ],
        "id": 11,
        "boxes": [
            [
                50,
                934,
                110,
                948
            ]
        ],
        "links": []
    },
    {
        "box": [
            541,
            589,
            575,
            602
        ],
        "text": "1500",
        "label": "ANSWER",
        "words": [
            "1500"
        ],
        "id": 12,
        "boxes": [
            [
                541,
                589,
                575,
                602
            ]
        ],
        "links": [
            [
                38,
                12
            ]
        ]
    },
    {
        "box": [
            549,
            615,
            576,
            630
        ],
        "text": "500",
        "label": "ANSWER",
        "words": [
            "500"
        ],
        "id": 13,
        "boxes": [
            [
                549,
                615,
                576,
                630
            ]
        ],
        "links": [
            [
                38,
                13
            ]
        ]
    },
    {
        "text": "K. A. SPARROW",
        "box": [
            215,
            124,
            304,
            139
        ],
        "label": "ANSWER",
        "words": [
            "K.",
            "A.",
            "SPARROW"
        ],
        "id": 14,
        "boxes": [
            [
                215,
                126,
                228,
                139
            ],
            [
                232,
                124,
                243,
                138
            ],
            [
                244,
                127,
                304,
                138
            ]
        ],
        "links": [
            [
                0,
                14
            ]
        ]
    },
    {
        "text": "DATE TO NYO:",
        "box": [
            499,
            126,
            584,
            141
        ],
        "label": "QUESTION",
        "words": [
            "DATE",
            "TO",
            "NYO:"
        ],
        "id": 15,
        "boxes": [
            [
                499,
                127,
                533,
                138
            ],
            [
                532,
                126,
                552,
                139
            ],
            [
                552,
                128,
                584,
                141
            ]
        ],
        "links": [
            [
                15,
                2
            ]
        ]
    },
    {
        "text": "S. Reindel",
        "box": [
            216,
            149,
            298,
            166
        ],
        "label": "ANSWER",
        "words": [
            "S.",
            "Reindel"
        ],
        "id": 16,
        "boxes": [
            [
                216,
                151,
                233,
                164
            ],
            [
                244,
                149,
                298,
                166
            ]
        ],
        "links": [
            [
                1,
                16
            ]
        ]
    },
    {
        "text": "Nassau/ 107",
        "box": [
            216,
            179,
            319,
            194
        ],
        "label": "ANSWER",
        "words": [
            "Nassau/",
            "107"
        ],
        "id": 17,
        "boxes": [
            [
                216,
                179,
                283,
                193
            ],
            [
                292,
                179,
                319,
                194
            ]
        ],
        "links": [
            [
                18,
                17
            ]
        ]
    },
    {
        "text": "DIV. NAME/ NO:",
        "box": [
            78,
            177,
            179,
            193
        ],
        "label": "QUESTION",
        "words": [
            "DIV.",
            "NAME/",
            "NO:"
        ],
        "id": 18,
        "boxes": [
            [
                78,
                177,
                106,
                192
            ],
            [
                108,
                180,
                154,
                193
            ],
            [
                155,
                179,
                179,
                193
            ]
        ],
        "links": [
            [
                18,
                17
            ]
        ]
    },
    {
        "text": "1997 SPECIAL EVENT REQUEST FORM",
        "box": [
            258,
            233,
            485,
            247
        ],
        "label": "HEADER",
        "words": [
            "1997",
            "SPECIAL",
            "EVENT",
            "REQUEST",
            "FORM"
        ],
        "id": 19,
        "boxes": [
            [
                258,
                233,
                282,
                247
            ],
            [
                286,
                235,
                339,
                246
            ],
            [
                339,
                235,
                381,
                246
            ],
            [
                384,
                235,
                444,
                246
            ],
            [
                447,
                235,
                485,
                246
            ]
        ],
        "links": []
    },
    {
        "text": "NAME OF EVENT:",
        "box": [
            77,
            288,
            185,
            302
        ],
        "label": "QUESTION",
        "words": [
            "NAME",
            "OF",
            "EVENT:"
        ],
        "id": 20,
        "boxes": [
            [
                77,
                288,
                116,
                301
            ],
            [
                117,
                288,
                135,
                301
            ],
            [
                138,
                288,
                185,
                302
            ]
        ],
        "links": [
            [
                20,
                23
            ]
        ]
    },
    {
        "text": "\"DATE OF EVENT:",
        "box": [
            81,
            314,
            188,
            330
        ],
        "label": "QUESTION",
        "words": [
            "\"DATE",
            "OF",
            "EVENT:"
        ],
        "id": 21,
        "boxes": [
            [
                81,
                316,
                117,
                330
            ],
            [
                122,
                317,
                139,
                328
            ],
            [
                141,
                314,
                188,
                328
            ]
        ],
        "links": [
            [
                21,
                22
            ]
        ]
    },
    {
        "text": "3/18/97",
        "box": [
            228,
            314,
            285,
            328
        ],
        "label": "ANSWER",
        "words": [
            "3/18/97"
        ],
        "id": 22,
        "boxes": [
            [
                228,
                314,
                285,
                328
            ]
        ],
        "links": [
            [
                21,
                22
            ]
        ]
    },
    {
        "text": "H. Levinson Tradeshow",
        "box": [
            216,
            286,
            395,
            303
        ],
        "label": "ANSWER",
        "words": [
            "H.",
            "Levinson",
            "Tradeshow"
        ],
        "id": 23,
        "boxes": [
            [
                216,
                288,
                233,
                303
            ],
            [
                243,
                288,
                311,
                302
            ],
            [
                320,
                286,
                395,
                301
            ]
        ],
        "links": [
            [
                20,
                23
            ]
        ]
    },
    {
        "text": "SAMPLE 10'S (400 PACKS PER CASE)",
        "box": [
            272,
            370,
            471,
            386
        ],
        "label": "ANSWER",
        "words": [
            "SAMPLE",
            "10'S",
            "(400",
            "PACKS",
            "PER",
            "CASE)"
        ],
        "id": 24,
        "boxes": [
            [
                272,
                372,
                319,
                385
            ],
            [
                325,
                370,
                345,
                383
            ],
            [
                348,
                373,
                370,
                384
            ],
            [
                369,
                372,
                408,
                385
            ],
            [
                409,
                370,
                433,
                384
            ],
            [
                437,
                372,
                471,
                386
            ]
        ],
        "links": [
            [
                25,
                24
            ]
        ]
    },
    {
        "text": "SAMPLES/ ITEMS REQUIRED:",
        "box": [
            75,
            372,
            260,
            385
        ],
        "label": "QUESTION",
        "words": [
            "SAMPLES/",
            "ITEMS",
            "REQUIRED:"
        ],
        "id": 25,
        "boxes": [
            [
                75,
                372,
                142,
                383
            ],
            [
                145,
                373,
                184,
                384
            ],
            [
                186,
                372,
                260,
                385
            ]
        ],
        "links": [
            [
                25,
                24
            ]
        ]
    },
    {
        "text": "NEWPORT K. S.",
        "box": [
            74,
            453,
            159,
            466
        ],
        "label": "QUESTION",
        "words": [
            "NEWPORT",
            "K.",
            "S."
        ],
        "id": 26,
        "boxes": [
            [
                74,
                453,
                137,
                466
            ],
            [
                138,
                453,
                149,
                466
            ],
            [
                148,
                453,
                159,
                466
            ]
        ],
        "links": [
            [
                26,
                3
            ]
        ]
    },
    {
        "text": "NEWPORT 100's",
        "box": [
            75,
            468,
            167,
            481
        ],
        "label": "QUESTION",
        "words": [
            "NEWPORT",
            "100's"
        ],
        "id": 27,
        "boxes": [
            [
                75,
                468,
                136,
                481
            ],
            [
                140,
                468,
                167,
                479
            ]
        ],
        "links": []
    },
    {
        "text": "NEWPORT LTS K. S.",
        "box": [
            77,
            480,
            186,
            494
        ],
        "label": "QUESTION",
        "words": [
            "NEWPORT",
            "LTS",
            "K.",
            "S."
        ],
        "id": 28,
        "boxes": [
            [
                77,
                482,
                137,
                492
            ],
            [
                138,
                480,
                162,
                494
            ],
            [
                163,
                480,
                176,
                494
            ],
            [
                176,
                480,
                186,
                493
            ]
        ],
        "links": [
            [
                28,
                4
            ]
        ]
    },
    {
        "text": "NEWPORT LTS. 100",
        "box": [
            77,
            494,
            184,
            507
        ],
        "label": "QUESTION",
        "words": [
            "NEWPORT",
            "LTS.",
            "100"
        ],
        "id": 29,
        "boxes": [
            [
                77,
                494,
                134,
                505
            ],
            [
                138,
                494,
                162,
                507
            ],
            [
                166,
                496,
                184,
                507
            ]
        ],
        "links": []
    },
    {
        "text": "KENT III K. S.",
        "box": [
            306,
            454,
            379,
            465
        ],
        "label": "QUESTION",
        "words": [
            "KENT",
            "III",
            "K.",
            "S."
        ],
        "id": 30,
        "boxes": [
            [
                306,
                454,
                340,
                464
            ],
            [
                342,
                454,
                356,
                465
            ],
            [
                355,
                454,
                368,
                464
            ],
            [
                369,
                454,
                379,
                464
            ]
        ],
        "links": []
    },
    {
        "text": "# CASES",
        "box": [
            307,
            426,
            359,
            439
        ],
        "label": "OTHER",
        "words": [
            "#",
            "CASES"
        ],
        "id": 31,
        "boxes": [
            [
                307,
                429,
                317,
                437
            ],
            [
                320,
                426,
                359,
                439
            ]
        ],
        "links": []
    },
    {
        "text": "KENT GL LTS K. S.",
        "box": [
            496,
            453,
            595,
            467
        ],
        "label": "QUESTION",
        "words": [
            "KENT",
            "GL",
            "LTS",
            "K.",
            "S."
        ],
        "id": 32,
        "boxes": [
            [
                496,
                454,
                531,
                465
            ],
            [
                532,
                454,
                549,
                467
            ],
            [
                552,
                455,
                573,
                466
            ],
            [
                574,
                453,
                585,
                466
            ],
            [
                587,
                455,
                595,
                465
            ]
        ],
        "links": []
    },
    {
        "text": "GL 100",
        "box": [
            497,
            468,
            573,
            479
        ],
        "label": "QUESTION",
        "words": [
            "",
            "GL",
            "100"
        ],
        "id": 33,
        "boxes": [
            [
                497,
                469,
                532,
                477
            ],
            [
                535,
                468,
                553,
                479
            ],
            [
                553,
                469,
                573,
                477
            ]
        ],
        "links": []
    },
    {
        "text": "KENT III 100",
        "box": [
            306,
            466,
            376,
            479
        ],
        "label": "QUESTION",
        "words": [
            "KENT",
            "III",
            "100"
        ],
        "id": 34,
        "boxes": [
            [
                306,
                466,
                340,
                479
            ],
            [
                342,
                469,
                356,
                477
            ],
            [
                358,
                469,
                376,
                479
            ]
        ],
        "links": []
    },
    {
        "text": "TRUE K. S.",
        "box": [
            306,
            480,
            363,
            493
        ],
        "label": "QUESTION",
        "words": [
            "TRUE",
            "K.",
            "S."
        ],
        "id": 35,
        "boxes": [
            [
                306,
                483,
                342,
                491
            ],
            [
                344,
                480,
                352,
                493
            ],
            [
                353,
                480,
                363,
                491
            ]
        ],
        "links": [
            [
                35,
                5
            ]
        ]
    },
    {
        "text": "KENT K. S.",
        "box": [
            306,
            496,
            363,
            508
        ],
        "label": "QUESTION",
        "words": [
            "KENT",
            "K.",
            "S."
        ],
        "id": 36,
        "boxes": [
            [
                306,
                496,
                340,
                504
            ],
            [
                342,
                497,
                353,
                508
            ],
            [
                352,
                496,
                363,
                507
            ]
        ],
        "links": [
            [
                36,
                6
            ]
        ]
    },
    {
        "text": "KENT 100",
        "box": [
            306,
            508,
            362,
            519
        ],
        "label": "QUESTION",
        "words": [
            "KENT",
            "100"
        ],
        "id": 37,
        "boxes": [
            [
                306,
                508,
                340,
                519
            ],
            [
                342,
                508,
                362,
                519
            ]
        ],
        "links": []
    },
    {
        "text": "QUANTITY REQUIRED",
        "box": [
            499,
            564,
            634,
            575
        ],
        "label": "QUESTION",
        "words": [
            "QUANTITY",
            "REQUIRED"
        ],
        "id": 38,
        "boxes": [
            [
                499,
                564,
                567,
                575
            ],
            [
                570,
                564,
                634,
                575
            ]
        ],
        "links": [
            [
                38,
                12
            ],
            [
                38,
                13
            ]
        ]
    },
    {
        "text": "BASEBALL CAP",
        "box": [
            304,
            589,
            400,
            603
        ],
        "label": "ANSWER",
        "words": [
            "BASEBALL",
            "CAP"
        ],
        "id": 39,
        "boxes": [
            [
                304,
                589,
                371,
                603
            ],
            [
                376,
                591,
                400,
                602
            ]
        ],
        "links": [
            [
                7,
                39
            ]
        ]
    },
    {
        "text": "WATER BOTTLES",
        "box": [
            307,
            620,
            413,
            633
        ],
        "label": "ANSWER",
        "words": [
            "WATER",
            "BOTTLES"
        ],
        "id": 40,
        "boxes": [
            [
                307,
                620,
                354,
                631
            ],
            [
                356,
                620,
                413,
                633
            ]
        ],
        "links": [
            [
                7,
                40
            ]
        ]
    },
    {
        "text": "SHIP TO:",
        "box": [
            77,
            728,
            131,
            741
        ],
        "label": "HEADER",
        "words": [
            "SHIP",
            "TO:"
        ],
        "id": 41,
        "boxes": [
            [
                77,
                728,
                105,
                741
            ],
            [
                109,
                728,
                131,
                739
            ]
        ],
        "links": [
            [
                41,
                42
            ]
        ]
    },
    {
        "text": "CUSTOMER SHIPPING NUMBER",
        "box": [
            78,
            756,
            257,
            767
        ],
        "label": "QUESTION",
        "words": [
            "CUSTOMER",
            "SHIPPING",
            "NUMBER"
        ],
        "id": 42,
        "boxes": [
            [
                78,
                757,
                142,
                767
            ],
            [
                145,
                756,
                199,
                767
            ],
            [
                204,
                757,
                257,
                765
            ]
        ],
        "links": [
            [
                41,
                42
            ],
            [
                42,
                43
            ]
        ]
    },
    {
        "text": "198- 1160006",
        "box": [
            324,
            754,
            405,
            768
        ],
        "label": "ANSWER",
        "words": [
            "198-",
            "1160006"
        ],
        "id": 43,
        "boxes": [
            [
                324,
                754,
                345,
                768
            ],
            [
                346,
                754,
                405,
                767
            ]
        ],
        "links": [
            [
                42,
                43
            ]
        ]
    },
    {
        "text": "NYO ONLY:",
        "box": [
            77,
            796,
            151,
            808
        ],
        "label": "HEADER",
        "words": [
            "NYO",
            "ONLY:"
        ],
        "id": 44,
        "boxes": [
            [
                77,
                797,
                106,
                808
            ],
            [
                110,
                796,
                151,
                807
            ]
        ],
        "links": [
            [
                44,
                45
            ]
        ]
    },
    {
        "text": "DATE FORWARDED TO PROMOTION SERVICES:",
        "box": [
            74,
            823,
            345,
            836
        ],
        "label": "QUESTION",
        "words": [
            "DATE",
            "FORWARDED",
            "TO",
            "PROMOTION",
            "SERVICES:"
        ],
        "id": 45,
        "boxes": [
            [
                74,
                825,
                109,
                835
            ],
            [
                112,
                825,
                190,
                835
            ],
            [
                191,
                823,
                208,
                836
            ],
            [
                209,
                825,
                284,
                835
            ],
            [
                285,
                825,
                345,
                835
            ]
        ],
        "links": [
            [
                44,
                45
            ],
            [
                45,
                8
            ]
        ]
    },
    {
        "text": "PLEASE ALLOW 6 WEEKS FOR PROCESSING OF YOUR REQUEST",
        "box": [
            77,
            877,
            472,
            893
        ],
        "label": "OTHER",
        "words": [
            "PLEASE",
            "ALLOW",
            "6",
            "WEEKS",
            "FOR",
            "PROCESSING",
            "OF",
            "YOUR",
            "REQUEST"
        ],
        "id": 46,
        "boxes": [
            [
                77,
                878,
                136,
                891
            ],
            [
                138,
                878,
                184,
                891
            ],
            [
                184,
                880,
                194,
                890
            ],
            [
                193,
                878,
                238,
                891
            ],
            [
                239,
                880,
                268,
                893
            ],
            [
                271,
                880,
                349,
                893
            ],
            [
                352,
                880,
                373,
                893
            ],
            [
                370,
                878,
                409,
                891
            ],
            [
                412,
                877,
                472,
                891
            ]
        ],
        "links": []
    }
]