[
    {
        "box": [
            149,
            292,
            188,
            305
        ],
        "text": "NAME",
        "label": "QUESTION",
        "words": [
            "NAME"
        ],
        "id": 0,
        "boxes": [
            [
                149,
                292,
                188,
                305
            ]
        ],
        "links": []
    },
    {
        "box": [
            148,
            318,
            212,
            336
        ],
        "text": "ADDRESS",
        "label": "QUESTION",
        "words": [
            "ADDRESS"
        ],
        "id": 1,
        "boxes": [
            [
                148,
                318,
                212,
                336
            ]
        ],
        "links": []
    },
    {
        "box": [
            149,
            348,
            185,
            365
        ],
        "text": "CITY",
        "label": "QUESTION",
        "words": [
            "CITY"
        ],
        "id": 2,
        "boxes": [
            [
                149,
                348,
                185,
                365
            ]
        ],
        "links": []
    },
    {
        "box": [
            321,
            348,
            364,
            366
        ],
        "text": "STATE",
        "label": "QUESTION",
        "words": [
            "STATE"
        ],
        "id": 3,
        "boxes": [
            [
                321,
                348,
                364,
                366
            ]
        ],
        "links": []
    },
    {
        "box": [
            490,
            349,
            518,
            367
        ],
        "text": "ZIP",
        "label": "QUESTION",
        "words": [
            "ZIP"
        ],
        "id": 4,
        "boxes": [
            [
                490,
                349,
                518,
                367
            ]
        ],
        "links": []
    },
    {
        "box": [
            149,
            492,
            178,
            506
        ],
        "text": "AGE",
        "label": "QUESTION",
        "words": [
            "AGE"
        ],
        "id": 5,
        "boxes": [
            [
                149,
                492,
                178,
                506
            ]
        ],
        "links": []
    },
    {
        "box": [
            173,
            633,
            190,
            651
        ],
        "text": "1.",
        "label": "QUESTION",
        "words": [
            "1."
        ],
        "id": 6,
        "boxes": [
            [
                173,
                633,
                190,
                651
            ]
        ],
        "links": []
    },
    {
        "box": [
            175,
            662,
            189,
            679
        ],
        "text": "2.",
        "label": "QUESTION",
        "words": [
            "2."
        ],
        "id": 7,
        "boxes": [
            [
                175,
                662,
                189,
                679
            ]
        ],
        "links": []
    },
    {
        "box": [
            175,
            689,
            189,
            709
        ],
        "text": "3.",
        "label": "QUESTION",
        "words": [
            "3."
        ],
        "id": 8,
        "boxes": [
            [
                175,
                689,
                189,
                709
            ]
        ],
        "links": []
    },
    {
        "box": [
            373,
            779,
            433,
            796
        ],
        "text": "SMOKING",
        "label": "QUESTION",
        "words": [
            "SMOKING"
        ],
        "id": 9,
        "boxes": [
            [
                373,
                779,
                433,
                796
            ]
        ],
        "links": []
    },
    {
        "box": [
            663,
            779,
            681,
            867
        ],
        "text": "85201976",
        "label": "OTHER",
        "words": [
            "85201976"
        ],
        "id": 10,
        "boxes": [
            [
                663,
                779,
                681,
                867
            ]
        ],
        "links": []
    },
    {
        "text": "Marden - Kane, Inc.",
        "box": [
            67,
            75,
            295,
            102
        ],
        "label": "HEADER",
        "words": [
            "Marden",
            "-",
            "Kane,",
            "Inc."
        ],
        "id": 11,
        "boxes": [
            [
                67,
                77,
                155,
                102
            ],
            [
                155,
                75,
                173,
                100
            ],
            [
                173,
                80,
                240,
                100
            ],
            [
                250,
                82,
                295,
                102
            ]
        ],
        "links": []
    },
    {
        "text": "TRUE \"YOU FOUND IT\" SWEEPSTAKES SECOND PRIZE WINNER TRAVEL INFORMATION SHEET",
        "box": [
            244,
            131,
            512,
            206
        ],
        "label": "OTHER",
        "words": [
            "TRUE",
            "\"YOU",
            "FOUND",
            "IT\"",
            "SWEEPSTAKES",
            "SECOND",
            "PRIZE",
            "WINNER",
            "TRAVEL",
            "INFORMATION",
            "SHEET"
        ],
        "id": 12,
        "boxes": [
            [
                244,
                131,
                279,
                148
            ],
            [
                286,
                133,
                322,
                150
            ],
            [
                328,
                133,
                374,
                148
            ],
            [
                380,
                134,
                407,
                148
            ],
            [
                413,
                134,
                512,
                149
            ],
            [
                274,
                163,
                328,
                180
            ],
            [
                337,
                161,
                382,
                178
            ],
            [
                387,
                163,
                446,
                176
            ],
            [
                275,
                189,
                328,
                204
            ],
            [
                334,
                189,
                436,
                206
            ],
            [
                440,
                191,
                486,
                205
            ]
        ],
        "links": []
    },
    {
        "text": "THE DESTINATION IN THE CONTINENTAL UNITED STATES I WISH TO TRAVEL TO IS:",
        "box": [
            145,
            233,
            616,
            266
        ],
        "label": "QUESTION",
        "words": [
            "THE",
            "DESTINATION",
            "IN",
            "THE",
            "CONTINENTAL",
            "UNITED",
            "STATES",
            "I",
            "WISH",
            "TO",
            "TRAVEL",
            "TO",
            "IS:"
        ],
        "id": 13,
        "boxes": [
            [
                145,
                233,
                174,
                250
            ],
            [
                184,
                233,
                278,
                253
            ],
            [
                286,
                236,
                303,
                250
            ],
            [
                311,
                235,
                336,
                250
            ],
            [
                342,
                236,
                441,
                250
            ],
            [
                446,
                236,
                499,
                250
            ],
            [
                504,
                236,
                558,
                250
            ],
            [
                561,
                236,
                576,
                250
            ],
            [
                581,
                237,
                616,
                250
            ],
            [
                149,
                253,
                169,
                266
            ],
            [
                177,
                251,
                229,
                265
            ],
            [
                236,
                250,
                257,
                265
            ],
            [
                265,
                253,
                289,
                266
            ]
        ],
        "links": []
    },
    {
        "text": "HOME PHONE",
        "box": [
            148,
            388,
            239,
            406
        ],
        "label": "QUESTION",
        "words": [
            "HOME",
            "PHONE"
        ],
        "id": 14,
        "boxes": [
            [
                148,
                388,
                184,
                405
            ],
            [
                193,
                391,
                239,
                406
            ]
        ],
        "links": []
    },
    {
        "text": "BUSINESS PHONE",
        "box": [
            149,
            420,
            272,
            435
        ],
        "label": "QUESTION",
        "words": [
            "BUSINESS",
            "PHONE"
        ],
        "id": 15,
        "boxes": [
            [
                149,
                420,
                220,
                435
            ],
            [
                226,
                420,
                272,
                435
            ]
        ],
        "links": []
    },
    {
        "text": "NAME OF GUEST",
        "box": [
            148,
            461,
            265,
            479
        ],
        "label": "QUESTION",
        "words": [
            "NAME",
            "OF",
            "GUEST"
        ],
        "id": 16,
        "boxes": [
            [
                148,
                462,
                187,
                479
            ],
            [
                191,
                461,
                211,
                478
            ],
            [
                219,
                462,
                265,
                477
            ]
        ],
        "links": []
    },
    {
        "text": "RELATIONSHIP TO WINNER",
        "box": [
            152,
            520,
            255,
            550
        ],
        "label": "QUESTION",
        "words": [
            "RELATIONSHIP",
            "TO",
            "WINNER"
        ],
        "id": 17,
        "boxes": [
            [
                152,
                520,
                255,
                534
            ],
            [
                158,
                538,
                180,
                548
            ],
            [
                187,
                535,
                240,
                550
            ]
        ],
        "links": []
    },
    {
        "text": "PLEASE LIST THREE ALTERNATIVE DATES YOU WOULD LIKE TO TRAVEL",
        "box": [
            149,
            589,
            666,
            609
        ],
        "label": "QUESTION",
        "words": [
            "PLEASE",
            "LIST",
            "THREE",
            "ALTERNATIVE",
            "DATES",
            "YOU",
            "WOULD",
            "LIKE",
            "TO",
            "TRAVEL"
        ],
        "id": 18,
        "boxes": [
            [
                149,
                591,
                203,
                608
            ],
            [
                211,
                591,
                247,
                605
            ],
            [
                253,
                592,
                296,
                609
            ],
            [
                306,
                591,
                398,
                606
            ],
            [
                405,
                589,
                450,
                604
            ],
            [
                459,
                591,
                484,
                606
            ],
            [
                494,
                592,
                536,
                607
            ],
            [
                543,
                592,
                578,
                606
            ],
            [
                584,
                592,
                604,
                606
            ],
            [
                612,
                594,
                666,
                608
            ]
        ],
        "links": []
    },
    {
        "text": "MAJOR AIRPORT NEAREST YOUR HOME",
        "box": [
            149,
            723,
            308,
            756
        ],
        "label": "QUESTION",
        "words": [
            "MAJOR",
            "AIRPORT",
            "NEAREST",
            "YOUR",
            "HOME"
        ],
        "id": 19,
        "boxes": [
            [
                149,
                723,
                196,
                740
            ],
            [
                205,
                725,
                265,
                740
            ],
            [
                159,
                739,
                222,
                756
            ],
            [
                228,
                742,
                267,
                753
            ],
            [
                272,
                740,
                308,
                753
            ]
        ],
        "links": []
    },
    {
        "text": "AIRLINE: (CHECK ONE)",
        "box": [
            152,
            768,
            246,
            797
        ],
        "label": "QUESTION",
        "words": [
            "AIRLINE:",
            "(CHECK",
            "ONE)"
        ],
        "id": 20,
        "boxes": [
            [
                152,
                768,
                219,
                779
            ],
            [
                152,
                784,
                204,
                797
            ],
            [
                208,
                781,
                246,
                796
            ]
        ],
        "links": []
    },
    {
        "text": "NON- SMOKING",
        "box": [
            552,
            784,
            649,
            798
        ],
        "label": "QUESTION",
        "words": [
            "NON-",
            "SMOKING"
        ],
        "id": 21,
        "boxes": [
            [
                552,
                784,
                588,
                798
            ],
            [
                588,
                784,
                649,
                798
            ]
        ],
        "links": []
    },
    {
        "text": "SPECIAL DIETARY REQUIREMENTS",
        "box": [
            152,
            824,
            396,
            841
        ],
        "label": "QUESTION",
        "words": [
            "SPECIAL",
            "DIETARY",
            "REQUIREMENTS"
        ],
        "id": 22,
        "boxes": [
            [
                152,
                824,
                213,
                839
            ],
            [
                221,
                824,
                282,
                839
            ],
            [
                288,
                824,
                396,
                841
            ]
        ],
        "links": []
    },
    {
        "text": "ANY ADDITIONAL INFORMATION YOU WOULD LIKE TO PROVIDE",
        "box": [
            149,
            852,
            487,
            884
        ],
        "label": "QUESTION",
        "words": [
            "ANY",
            "ADDITIONAL",
            "INFORMATION",
            "YOU",
            "WOULD",
            "LIKE",
            "TO",
            "PROVIDE"
        ],
        "id": 23,
        "boxes": [
            [
                149,
                853,
                181,
                867
            ],
            [
                184,
                852,
                275,
                866
            ],
            [
                166,
                867,
                265,
                882
            ],
            [
                271,
                867,
                299,
                881
            ],
            [
                306,
                869,
                351,
                882
            ],
            [
                356,
                867,
                394,
                881
            ],
            [
                398,
                867,
                419,
                882
            ],
            [
                426,
                869,
                487,
                884
            ]
        ],
        "links": []
    }
]