[
    {
        "box": [
            168,
            261,
            192,
            276
        ],
        "text": "To:",
        "label": "QUESTION",
        "words": [
            "To:"
        ],
        "id": 0,
        "boxes": [
            [
                168,
                261,
                192,
                276
            ]
        ],
        "links": [
            [
                0,
                12
            ]
        ]
    },
    {
        "box": [
            168,
            282,
            204,
            297
        ],
        "text": "Firm:",
        "label": "QUESTION",
        "words": [
            "Firm:"
        ],
        "id": 1,
        "boxes": [
            [
                168,
                282,
                204,
                297
            ]
        ],
        "links": [
            [
                1,
                6
            ]
        ]
    },
    {
        "box": [
            169,
            304,
            196,
            319
        ],
        "text": "FAX",
        "label": "QUESTION",
        "words": [
            "FAX"
        ],
        "id": 2,
        "boxes": [
            [
                169,
                304,
                196,
                319
            ]
        ],
        "links": [
            [
                2,
                7
            ]
        ]
    },
    {
        "box": [
            198,
            304,
            216,
            319
        ],
        "text": "#:",
        "label": "QUESTION",
        "words": [
            "#:"
        ],
        "id": 3,
        "boxes": [
            [
                198,
                304,
                216,
                319
            ]
        ],
        "links": []
    },
    {
        "box": [
            168,
            342,
            209,
            357
        ],
        "text": "From:",
        "label": "QUESTION",
        "words": [
            "From:"
        ],
        "id": 4,
        "boxes": [
            [
                168,
                342,
                209,
                357
            ]
        ],
        "links": [
            [
                4,
                13
            ]
        ]
    },
    {
        "box": [
            169,
            425,
            204,
            442
        ],
        "text": "Date:",
        "label": "QUESTION",
        "words": [
            "Date:"
        ],
        "id": 5,
        "boxes": [
            [
                169,
                425,
                204,
                442
            ]
        ],
        "links": [
            [
                5,
                18
            ]
        ]
    },
    {
        "box": [
            270,
            282,
            304,
            297
        ],
        "text": "MSA",
        "label": "ANSWER",
        "words": [
            "MSA"
        ],
        "id": 6,
        "boxes": [
            [
                270,
                282,
                304,
                297
            ]
        ],
        "links": [
            [
                1,
                6
            ]
        ]
    },
    {
        "box": [
            271,
            306,
            327,
            320
        ],
        "text": "Autodial",
        "label": "ANSWER",
        "words": [
            "Autodial"
        ],
        "id": 7,
        "boxes": [
            [
                271,
                306,
                327,
                320
            ]
        ],
        "links": [
            [
                2,
                7
            ]
        ]
    },
    {
        "box": [
            117,
            560,
            151,
            575
        ],
        "text": "Mike,",
        "label": "OTHER",
        "words": [
            "Mike,"
        ],
        "id": 8,
        "boxes": [
            [
                117,
                560,
                151,
                575
            ]
        ],
        "links": []
    },
    {
        "box": [
            258,
            761,
            310,
            782
        ],
        "text": "",
        "label": "OTHER",
        "words": [
            ""
        ],
        "id": 9,
        "boxes": [
            [
                258,
                761,
                310,
                782
            ]
        ],
        "links": []
    },
    {
        "box": [
            661,
            711,
            682,
            814
        ],
        "text": "8622042",
        "label": "OTHER",
        "words": [
            "8622042"
        ],
        "id": 10,
        "boxes": [
            [
                661,
                711,
                682,
                814
            ]
        ],
        "links": []
    },
    {
        "text": "LORILLARD TOBACCO COMPANY Market Planning and Information Department",
        "box": [
            198,
            182,
            506,
            222
        ],
        "label": "HEADER",
        "words": [
            "LORILLARD",
            "TOBACCO",
            "COMPANY",
            "Market",
            "Planning",
            "and",
            "Information",
            "Department"
        ],
        "id": 11,
        "boxes": [
            [
                237,
                184,
                318,
                198
            ],
            [
                321,
                182,
                395,
                199
            ],
            [
                398,
                182,
                473,
                199
            ],
            [
                198,
                205,
                245,
                220
            ],
            [
                249,
                205,
                310,
                222
            ],
            [
                314,
                208,
                341,
                219
            ],
            [
                345,
                205,
                422,
                220
            ],
            [
                426,
                204,
                506,
                222
            ]
        ],
        "links": []
    },
    {
        "text": "Mike Mozina",
        "box": [
            271,
            260,
            354,
            277
        ],
        "label": "ANSWER",
        "words": [
            "Mike",
            "Mozina"
        ],
        "id": 12,
        "boxes": [
            [
                271,
                260,
                303,
                277
            ],
            [
                307,
                260,
                354,
                274
            ]
        ],
        "links": [
            [
                0,
                12
            ]
        ]
    },
    {
        "text": "Susan Smith",
        "box": [
            271,
            342,
            358,
            359
        ],
        "label": "ANSWER",
        "words": [
            "Susan",
            "Smith"
        ],
        "id": 13,
        "boxes": [
            [
                271,
                342,
                310,
                359
            ],
            [
                317,
                342,
                358,
                357
            ]
        ],
        "links": [
            [
                4,
                13
            ]
        ]
    },
    {
        "text": "335- 7733",
        "box": [
            270,
            365,
            336,
            382
        ],
        "label": "ANSWER",
        "words": [
            "335-",
            "7733"
        ],
        "id": 14,
        "boxes": [
            [
                270,
                365,
                301,
                382
            ],
            [
                302,
                366,
                336,
                381
            ]
        ],
        "links": [
            [
                16,
                14
            ]
        ]
    },
    {
        "text": "335- 7150",
        "box": [
            271,
            388,
            335,
            403
        ],
        "label": "ANSWER",
        "words": [
            "335-",
            "7150"
        ],
        "id": 15,
        "boxes": [
            [
                271,
                388,
                300,
                402
            ],
            [
                300,
                388,
                335,
                403
            ]
        ],
        "links": [
            [
                17,
                15
            ]
        ]
    },
    {
        "text": "FAX #:",
        "box": [
            169,
            365,
            217,
            380
        ],
        "label": "QUESTION",
        "words": [
            "FAX",
            "#:"
        ],
        "id": 16,
        "boxes": [
            [
                169,
                365,
                196,
                379
            ],
            [
                200,
                366,
                217,
                380
            ]
        ],
        "links": [
            [
                16,
                14
            ]
        ]
    },
    {
        "text": "Phone #:",
        "box": [
            169,
            387,
            233,
            404
        ],
        "label": "QUESTION",
        "words": [
            "Phone",
            "#:"
        ],
        "id": 17,
        "boxes": [
            [
                169,
                388,
                212,
                402
            ],
            [
                215,
                387,
                233,
                404
            ]
        ],
        "links": [
            [
                17,
                15
            ]
        ]
    },
    {
        "text": "8/ 31/ 98",
        "box": [
            270,
            426,
            324,
            441
        ],
        "label": "ANSWER",
        "words": [
            "8/",
            "31/",
            "98"
        ],
        "id": 18,
        "boxes": [
            [
                270,
                426,
                284,
                440
            ],
            [
                285,
                426,
                305,
                441
            ],
            [
                306,
                426,
                324,
                439
            ]
        ],
        "links": [
            [
                5,
                18
            ]
        ]
    },
    {
        "text": "3 (including this cover page)",
        "box": [
            268,
            447,
            465,
            463
        ],
        "label": "ANSWER",
        "words": [
            "3",
            "(including",
            "this",
            "cover",
            "page)"
        ],
        "id": 19,
        "boxes": [
            [
                268,
                448,
                279,
                463
            ],
            [
                282,
                447,
                352,
                462
            ],
            [
                355,
                447,
                380,
                461
            ],
            [
                384,
                450,
                422,
                461
            ],
            [
                426,
                448,
                465,
                462
            ]
        ],
        "links": [
            [
                20,
                19
            ]
        ]
    },
    {
        "text": "# Pages:",
        "box": [
            168,
            447,
            230,
            464
        ],
        "label": "QUESTION",
        "words": [
            "#",
            "Pages:"
        ],
        "id": 20,
        "boxes": [
            [
                168,
                448,
                181,
                461
            ],
            [
                184,
                447,
                230,
                464
            ]
        ],
        "links": [
            [
                20,
                19
            ]
        ]
    },
    {
        "text": "- Approval for AWS Quarterly Store Count Database to begin 3rd Quarter 1998",
        "box": [
            117,
            647,
            612,
            664
        ],
        "label": "OTHER",
        "words": [
            "-",
            "Approval",
            "for",
            "AWS",
            "Quarterly",
            "Store",
            "Count",
            "Database",
            "to",
            "begin",
            "3rd",
            "Quarter",
            "1998"
        ],
        "id": 21,
        "boxes": [
            [
                117,
                654,
                127,
                661
            ],
            [
                130,
                649,
                186,
                664
            ],
            [
                189,
                649,
                207,
                663
            ],
            [
                209,
                648,
                241,
                663
            ],
            [
                244,
                648,
                303,
                663
            ],
            [
                306,
                648,
                340,
                663
            ],
            [
                344,
                649,
                383,
                663
            ],
            [
                385,
                648,
                445,
                663
            ],
            [
                448,
                649,
                461,
                660
            ],
            [
                464,
                647,
                500,
                662
            ],
            [
                504,
                648,
                525,
                662
            ],
            [
                528,
                647,
                577,
                661
            ],
            [
                580,
                647,
                612,
                660
            ]
        ],
        "links": []
    },
    {
        "text": "- Table showing significant jump in Convenience Store market importance in 2nd Quarter 1998",
        "box": [
            116,
            693,
            587,
            731
        ],
        "label": "OTHER",
        "words": [
            "-",
            "Table",
            "showing",
            "significant",
            "jump",
            "in",
            "Convenience",
            "Store",
            "market",
            "importance",
            "in",
            "2nd",
            "Quarter",
            "1998"
        ],
        "id": 22,
        "boxes": [
            [
                116,
                700,
                126,
                706
            ],
            [
                130,
                694,
                165,
                708
            ],
            [
                168,
                694,
                222,
                711
            ],
            [
                223,
                693,
                290,
                710
            ],
            [
                292,
                694,
                324,
                709
            ],
            [
                327,
                694,
                340,
                708
            ],
            [
                342,
                693,
                427,
                707
            ],
            [
                429,
                693,
                464,
                707
            ],
            [
                466,
                694,
                511,
                705
            ],
            [
                514,
                693,
                587,
                708
            ],
            [
                133,
                716,
                144,
                729
            ],
            [
                147,
                718,
                172,
                731
            ],
            [
                176,
                716,
                223,
                730
            ],
            [
                228,
                716,
                260,
                729
            ]
        ],
        "links": []
    },
    {
        "text": "Talk to you soon!",
        "box": [
            117,
            761,
            225,
            778
        ],
        "label": "QUESTION",
        "words": [
            "Talk",
            "to",
            "you",
            "soon!"
        ],
        "id": 23,
        "boxes": [
            [
                117,
                761,
                144,
                776
            ],
            [
                147,
                763,
                160,
                774
            ],
            [
                163,
                763,
                187,
                778
            ],
            [
                190,
                761,
                225,
                775
            ]
        ],
        "links": []
    },
    {
        "text": "As promised, here are:",
        "box": [
            117,
            605,
            260,
            622
        ],
        "label": "QUESTION",
        "words": [
            "As",
            "promised,",
            "here",
            "are:"
        ],
        "id": 24,
        "boxes": [
            [
                117,
                605,
                134,
                618
            ],
            [
                137,
                605,
                201,
                622
            ],
            [
                203,
                605,
                234,
                618
            ],
            [
                236,
                606,
                260,
                617
            ]
        ],
        "links": []
    }
]